{
  "type": "FeatureCollection",
  "features": [
    {
      "type": "Feature",
      "id": 5664095,
      "geometry": {
        "type": "Point",
        "coordinates": [
          -7.8776820004452333,
          40.66582699963066
        ]
      },
      "properties": {
        "OBJECTID": 5664095,
        "ID_oc": 26614984,
        "Numero": 20260092997,
        "Ano": null,
        "DataInicioOcorrencia": "2026-01-20T17:28:00",
        "DataOcorrencia": 1768933680000,
        "Data": 1768930080000,
        "Hora": null,
        "Duracao": null,
        "DuracaoMinutos": null,
        "FaseIncendio": null,
        "GrupoOc": null,
        "GrupoOc_ID": null,
        "CodNatureza": 2403,
        "IDFamilia": null,
        "Familia": null,
        "IDEspecie": null,
        "Especie": null,
        "IDTipo": null,
        "Tipo": null,
        "Natureza": "Colisão rodoviária",
        "CodImportancia": null,
        "Importancia": null,
        "CodEstadoOcorrencia": null,
        "EstadoOcorrencia": "Em Curso",
        "EstadoAgrupado": "Em Curso",
        "CREPC_ID": null,
        "CSREPC": "Viseu Dão Lafões",
        "CSREPC_ID": null,
        "CREPC": "Centro",
        "DI": null,
        "Distrito": null,
        "NUT_III": null,
        "CIM": null,
        "DICO": null,
        "Concelho": "Viseu",
        "DICOFRE": null,
        "Freguesia": "Rio de Loba",
        "Localidade": "RIO DE LOBA",
        "Endereco": null,
        "EntidadeResponsavel": null,
        "EntidadeGestora": null,
        "PCO": null,
        "COS": null,
        "UltimoPOSIT": null,
        "QuantEntidades": null,
        "RHBombeiros": null,
        "RHFEPC": null,
        "RHUEPS": null,
        "RHGNR": null,
        "RHPSP": null,
        "RHESF": null,
        "RHFA": null,
        "RHINEM": null,
        "RHOutros": null,
        "NumeroOperacionaisTerrestresEnv": null,
        "Operacionais": 6,
        "NumeroOperacionaisAereosEnvolvi": null,
        "RTBombeiros": null,
        "RTFEPC": null,
        "RTUEPS": null,
        "RTGNR": null,
        "RTPSP": null,
        "RTESF": null,
        "RTFA": null,
        "RTINEM": null,
        "RTOutros": null,
        "NumeroMeiosTerrestresEnvolvidos": 2,
        "GruposReforco": null,
        "HELigeiro": null,
        "HEPesado": null,
        "HECoordenacao": null,
        "HEOutro": null,
        "AVMedio": null,
        "AVPesado": null,
        "AVReconhecimento": null,
        "AVOutro": null,
        "NumeroMeiosAereosEnvolvidos": 0,
        "Latitude": 40.665827,
        "Longitude": -7.8776820000000001,
        "DDD": null,
        "DMM": null,
        "DMS": null,
        "DataDosDados": 1768931120000,
        "Simbol": "24 - Em Curso",
        "Status": 0,
        "Obs": null,
        "NumeroMeiosAquaticos": 0
      }
    },
    {
      "type": "Feature",
      "id": 5664096,
      "geometry": {
        "type": "Point",
        "coordinates": [
          -9.1523290004362945,
          38.737459999597192
        ]
      },
      "properties": {
        "OBJECTID": 5664096,
        "ID_oc": 26614887,
        "Numero": 20260092900,
        "Ano": null,
        "DataInicioOcorrencia": "2026-01-20T16:56:00",
        "DataOcorrencia": 1768931760000,
        "Data": 1768928160000,
        "Hora": null,
        "Duracao": null,
        "DuracaoMinutos": null,
        "FaseIncendio": null,
        "GrupoOc": null,
        "GrupoOc_ID": null,
        "CodNatureza": 2401,
        "IDFamilia": null,
        "Familia": null,
        "IDEspecie": null,
        "Especie": null,
        "IDTipo": null,
        "Tipo": null,
        "Natureza": "Atropelamento rodoviário",
        "CodImportancia": null,
        "Importancia": null,
        "CodEstadoOcorrencia": null,
        "EstadoOcorrencia": "Despacho de 1.º Alerta",
        "EstadoAgrupado": "Em Despacho",
        "CREPC_ID": null,
        "CSREPC": "Grande Lisboa",
        "CSREPC_ID": null,
        "CREPC": "Lisboa e Vale do Tejo",
        "DI": null,
        "Distrito": null,
        "NUT_III": null,
        "CIM": null,
        "DICO": null,
        "Concelho": "Lisboa",
        "DICOFRE": null,
        "Freguesia": "Avenidas Novas",
        "Localidade": "Avenidas Novas",
        "Endereco": null,
        "EntidadeResponsavel": null,
        "EntidadeGestora": null,
        "PCO": null,
        "COS": null,
        "UltimoPOSIT": null,
        "QuantEntidades": null,
        "RHBombeiros": null,
        "RHFEPC": null,
        "RHUEPS": null,
        "RHGNR": null,
        "RHPSP": null,
        "RHESF": null,
        "RHFA": null,
        "RHINEM": null,
        "RHOutros": null,
        "NumeroOperacionaisTerrestresEnv": null,
        "Operacionais": 2,
        "NumeroOperacionaisAereosEnvolvi": null,
        "RTBombeiros": null,
        "RTFEPC": null,
        "RTUEPS": null,
        "RTGNR": null,
        "RTPSP": null,
        "RTESF": null,
        "RTFA": null,
        "RTINEM": null,
        "RTOutros": null,
        "NumeroMeiosTerrestresEnvolvidos": 1,
        "GruposReforco": null,
        "HELigeiro": null,
        "HEPesado": null,
        "HECoordenacao": null,
        "HEOutro": null,
        "AVMedio": null,
        "AVPesado": null,
        "AVReconhecimento": null,
        "AVOutro": null,
        "NumeroMeiosAereosEnvolvidos": 0,
        "Latitude": 38.737459999999999,
        "Longitude": -9.1523289999999999,
        "DDD": null,
        "DMM": null,
        "DMS": null,
        "DataDosDados": 1768931120000,
        "Simbol": "24 - Em Despacho",
        "Status": 0,
        "Obs": null,
        "NumeroMeiosAquaticos": 0
      }
    },
    {
      "type": "Feature",
      "id": 5664097,
      "geometry": {
        "type": "Point",
        "coordinates": [
          -8.6937289996428859,
          41.294993000432029
        ]
      },
      "properties": {
        "OBJECTID": 5664097,
        "ID_oc": 26614367,
        "Numero": 20260092380,
        "Ano": null,
        "DataInicioOcorrencia": "2026-01-20T15:02:00",
        "DataOcorrencia": 1768924920000,
        "Data": 1768921320000,
        "Hora": null,
        "Duracao": null,
        "DuracaoMinutos": null,
        "FaseIncendio": null,
        "GrupoOc": null,
        "GrupoOc_ID": null,
        "CodNatureza": 3315,
        "IDFamilia": null,
        "Familia": null,
        "IDEspecie": null,
        "Especie": null,
        "IDTipo": null,
        "Tipo": null,
        "Natureza": "Inundação de estruturas ou superfícies por precipitação intensa",
        "CodImportancia": null,
        "Importancia": null,
        "CodEstadoOcorrencia": null,
        "EstadoOcorrencia": "Despacho de 1.º Alerta",
        "EstadoAgrupado": "Em Despacho",
        "CREPC_ID": null,
        "CSREPC": "Area M. Porto",
        "CSREPC_ID": null,
        "CREPC": "Norte",
        "DI": null,
        "Distrito": null,
        "NUT_III": null,
        "CIM": null,
        "DICO": null,
        "Concelho": "Vila do Conde",
        "DICOFRE": null,
        "Freguesia": "Modivas",
        "Localidade": "Caves do Retail Park",
        "Endereco": null,
        "EntidadeResponsavel": null,
        "EntidadeGestora": null,
        "PCO": null,
        "COS": null,
        "UltimoPOSIT": null,
        "QuantEntidades": null,
        "RHBombeiros": null,
        "RHFEPC": null,
        "RHUEPS": null,
        "RHGNR": null,
        "RHPSP": null,
        "RHESF": null,
        "RHFA": null,
        "RHINEM": null,
        "RHOutros": null,
        "NumeroOperacionaisTerrestresEnv": null,
        "Operacionais": 2,
        "NumeroOperacionaisAereosEnvolvi": null,
        "RTBombeiros": null,
        "RTFEPC": null,
        "RTUEPS": null,
        "RTGNR": null,
        "RTPSP": null,
        "RTESF": null,
        "RTFA": null,
        "RTINEM": null,
        "RTOutros": null,
        "NumeroMeiosTerrestresEnvolvidos": 1,
        "GruposReforco": null,
        "HELigeiro": null,
        "HEPesado": null,
        "HECoordenacao": null,
        "HEOutro": null,
        "AVMedio": null,
        "AVPesado": null,
        "AVReconhecimento": null,
        "AVOutro": null,
        "NumeroMeiosAereosEnvolvidos": 0,
        "Latitude": 41.294992999999998,
        "Longitude": -8.6937289999999994,
        "DDD": null,
        "DMM": null,
        "DMS": null,
        "DataDosDados": 1768931120000,
        "Simbol": "33 - Em Despacho",
        "Status": 0,
        "Obs": null,
        "NumeroMeiosAquaticos": 0
      }
    },
    {
      "type": "Feature",
      "id": 5664098,
      "geometry": {
        "type": "Point",
        "coordinates": [
          -7.8822750003132533,
          40.702758000065494
        ]
      },
      "properties": {
        "OBJECTID": 5664098,
        "ID_oc": 26614934,
        "Numero": 20260092947,
        "Ano": null,
        "DataInicioOcorrencia": "2026-01-20T16:30:00",
        "DataOcorrencia": 1768930200000,
        "Data": 1768926600000,
        "Hora": null,
        "Duracao": null,
        "DuracaoMinutos": null,
        "FaseIncendio": null,
        "GrupoOc": null,
        "GrupoOc_ID": null,
        "CodNatureza": 4331,
        "IDFamilia": null,
        "Familia": null,
        "IDEspecie": null,
        "Especie": null,
        "IDTipo": null,
        "Tipo": null,
        "Natureza": "Busca e Resgate Terrestre, de Animais",
        "CodImportancia": null,
        "Importancia": null,
        "CodEstadoOcorrencia": null,
        "EstadoOcorrencia": "Despacho de 1.º Alerta",
        "EstadoAgrupado": "Em Despacho",
        "CREPC_ID": null,
        "CSREPC": "Viseu Dão Lafões",
        "CSREPC_ID": null,
        "CREPC": "Centro",
        "DI": null,
        "Distrito": null,
        "NUT_III": null,
        "CIM": null,
        "DICO": null,
        "Concelho": "Viseu",
        "DICOFRE": null,
        "Freguesia": "Mundão",
        "Localidade": "Nespereira de Mundão",
        "Endereco": null,
        "EntidadeResponsavel": null,
        "EntidadeGestora": null,
        "PCO": null,
        "COS": null,
        "UltimoPOSIT": null,
        "QuantEntidades": null,
        "RHBombeiros": null,
        "RHFEPC": null,
        "RHUEPS": null,
        "RHGNR": null,
        "RHPSP": null,
        "RHESF": null,
        "RHFA": null,
        "RHINEM": null,
        "RHOutros": null,
        "NumeroOperacionaisTerrestresEnv": null,
        "Operacionais": 3,
        "NumeroOperacionaisAereosEnvolvi": null,
        "RTBombeiros": null,
        "RTFEPC": null,
        "RTUEPS": null,
        "RTGNR": null,
        "RTPSP": null,
        "RTESF": null,
        "RTFA": null,
        "RTINEM": null,
        "RTOutros": null,
        "NumeroMeiosTerrestresEnvolvidos": 1,
        "GruposReforco": null,
        "HELigeiro": null,
        "HEPesado": null,
        "HECoordenacao": null,
        "HEOutro": null,
        "AVMedio": null,
        "AVPesado": null,
        "AVReconhecimento": null,
        "AVOutro": null,
        "NumeroMeiosAereosEnvolvidos": 0,
        "Latitude": 40.702758000000003,
        "Longitude": -7.8822749999999999,
        "DDD": null,
        "DMM": null,
        "DMS": null,
        "DataDosDados": 1768931120000,
        "Simbol": "43 - Em Despacho",
        "Status": 0,
        "Obs": null,
        "NumeroMeiosAquaticos": 0
      }
    },
    {
      "type": "Feature",
      "id": 5664099,
      "geometry": {
        "type": "Point",
        "coordinates": [
          -7.2507120005439534,
          38.115065000054251
        ]
      },
      "properties": {
        "OBJECTID": 5664099,
        "ID_oc": 26614802,
        "Numero": 20260092815,
        "Ano": null,
        "DataInicioOcorrencia": "2026-01-20T16:46:00",
        "DataOcorrencia": 1768931160000,
        "Data": 1768927560000,
        "Hora": null,
        "Duracao": null,
        "DuracaoMinutos": null,
        "FaseIncendio": null,
        "GrupoOc": null,
        "GrupoOc_ID": null,
        "CodNatureza": 2407,
        "IDFamilia": null,
        "Familia": null,
        "IDEspecie": null,
        "Especie": null,
        "IDTipo": null,
        "Tipo": null,
        "Natureza": "Despiste",
        "CodImportancia": null,
        "Importancia": null,
        "CodEstadoOcorrencia": null,
        "EstadoOcorrencia": "Conclusão",
        "EstadoAgrupado": "Em Conclusão",
        "CREPC_ID": null,
        "CSREPC": "Baixo Alentejo",
        "CSREPC_ID": null,
        "CREPC": "Alentejo",
        "DI": null,
        "Distrito": null,
        "NUT_III": null,
        "CIM": null,
        "DICO": null,
        "Concelho": "Moura",
        "DICOFRE": null,
        "Freguesia": "Safara",
        "Localidade": "EN 258 KM 74.400",
        "Endereco": null,
        "EntidadeResponsavel": null,
        "EntidadeGestora": null,
        "PCO": null,
        "COS": null,
        "UltimoPOSIT": null,
        "QuantEntidades": null,
        "RHBombeiros": null,
        "RHFEPC": null,
        "RHUEPS": null,
        "RHGNR": null,
        "RHPSP": null,
        "RHESF": null,
        "RHFA": null,
        "RHINEM": null,
        "RHOutros": null,
        "NumeroOperacionaisTerrestresEnv": null,
        "Operacionais": 9,
        "NumeroOperacionaisAereosEnvolvi": null,
        "RTBombeiros": null,
        "RTFEPC": null,
        "RTUEPS": null,
        "RTGNR": null,
        "RTPSP": null,
        "RTESF": null,
        "RTFA": null,
        "RTINEM": null,
        "RTOutros": null,
        "NumeroMeiosTerrestresEnvolvidos": 4,
        "GruposReforco": null,
        "HELigeiro": null,
        "HEPesado": null,
        "HECoordenacao": null,
        "HEOutro": null,
        "AVMedio": null,
        "AVPesado": null,
        "AVReconhecimento": null,
        "AVOutro": null,
        "NumeroMeiosAereosEnvolvidos": 0,
        "Latitude": 38.115065000000001,
        "Longitude": -7.250712,
        "DDD": null,
        "DMM": null,
        "DMS": null,
        "DataDosDados": 1768931120000,
        "Simbol": "24 - Em Conclusão",
        "Status": 0,
        "Obs": null,
        "NumeroMeiosAquaticos": 0
      }
    },
    {
      "type": "Feature",
      "id": 5664100,
      "geometry": {
        "type": "Point",
        "coordinates": [
          -8.8394190004868047,
          41.867575000303994
        ]
      },
      "properties": {
        "OBJECTID": 5664100,
        "ID_oc": 26614985,
        "Numero": 20260092998,
        "Ano": null,
        "DataInicioOcorrencia": "2026-01-20T17:28:00",
        "DataOcorrencia": 1768933680000,
        "Data": 1768930080000,
        "Hora": null,
        "Duracao": null,
        "DuracaoMinutos": null,
        "FaseIncendio": null,
        "GrupoOc": null,
        "GrupoOc_ID": null,
        "CodNatureza": 2403,
        "IDFamilia": null,
        "Familia": null,
        "IDEspecie": null,
        "Especie": null,
        "IDTipo": null,
        "Tipo": null,
        "Natureza": "Colisão rodoviária",
        "CodImportancia": null,
        "Importancia": null,
        "CodEstadoOcorrencia": null,
        "EstadoOcorrencia": "Despacho de 1.º Alerta",
        "EstadoAgrupado": "Em Despacho",
        "CREPC_ID": null,
        "CSREPC": "Alto Minho",
        "CSREPC_ID": null,
        "CREPC": "Norte",
        "DI": null,
        "Distrito": null,
        "NUT_III": null,
        "CIM": null,
        "DICO": null,
        "Concelho": "Caminha",
        "DICOFRE": null,
        "Freguesia": "Caminha (Matriz) e Vilarelho",
        "Localidade": "EN13",
        "Endereco": null,
        "EntidadeResponsavel": null,
        "EntidadeGestora": null,
        "PCO": null,
        "COS": null,
        "UltimoPOSIT": null,
        "QuantEntidades": null,
        "RHBombeiros": null,
        "RHFEPC": null,
        "RHUEPS": null,
        "RHGNR": null,
        "RHPSP": null,
        "RHESF": null,
        "RHFA": null,
        "RHINEM": null,
        "RHOutros": null,
        "NumeroOperacionaisTerrestresEnv": null,
        "Operacionais": 3,
        "NumeroOperacionaisAereosEnvolvi": null,
        "RTBombeiros": null,
        "RTFEPC": null,
        "RTUEPS": null,
        "RTGNR": null,
        "RTPSP": null,
        "RTESF": null,
        "RTFA": null,
        "RTINEM": null,
        "RTOutros": null,
        "NumeroMeiosTerrestresEnvolvidos": 1,
        "GruposReforco": null,
        "HELigeiro": null,
        "HEPesado": null,
        "HECoordenacao": null,
        "HEOutro": null,
        "AVMedio": null,
        "AVPesado": null,
        "AVReconhecimento": null,
        "AVOutro": null,
        "NumeroMeiosAereosEnvolvidos": 0,
        "Latitude": 41.867575000000002,
        "Longitude": -8.8394189999999995,
        "DDD": null,
        "DMM": null,
        "DMS": null,
        "DataDosDados": 1768931120000,
        "Simbol": "24 - Em Despacho",
        "Status": 0,
        "Obs": null,
        "NumeroMeiosAquaticos": 0
      }
    },
    {
      "type": "Feature",
      "id": 5664101,
      "geometry": {
        "type": "Point",
        "coordinates": [
          -8.6769799998740691,
          41.165829999923702
        ]
      },
      "properties": {
        "OBJECTID": 5664101,
        "ID_oc": 26614669,
        "Numero": 20260092682,
        "Ano": null,
        "DataInicioOcorrencia": "2026-01-20T16:20:00",
        "DataOcorrencia": 1768929600000,
        "Data": 1768926000000,
        "Hora": null,
        "Duracao": null,
        "DuracaoMinutos": null,
        "FaseIncendio": null,
        "GrupoOc": null,
        "GrupoOc_ID": null,
        "CodNatureza": 2129,
        "IDFamilia": null,
        "Familia": null,
        "IDEspecie": null,
        "Especie": null,
        "IDTipo": null,
        "Tipo": null,
        "Natureza": "Edifícios degradados ou devolutos",
        "CodImportancia": null,
        "Importancia": null,
        "CodEstadoOcorrencia": null,
        "EstadoOcorrencia": "Conclusão",
        "EstadoAgrupado": "Em Conclusão",
        "CREPC_ID": null,
        "CSREPC": "Area M. Porto",
        "CSREPC_ID": null,
        "CREPC": "Norte",
        "DI": null,
        "Distrito": null,
        "NUT_III": null,
        "CIM": null,
        "DICO": null,
        "Concelho": "Porto",
        "DICOFRE": null,
        "Freguesia": "Aldoar, Foz do Douro e Nevogilde",
        "Localidade": "União das Freguesias de Aldoar, Foz do Douro e Nevogilde",
        "Endereco": null,
        "EntidadeResponsavel": null,
        "EntidadeGestora": null,
        "PCO": null,
        "COS": null,
        "UltimoPOSIT": null,
        "QuantEntidades": null,
        "RHBombeiros": null,
        "RHFEPC": null,
        "RHUEPS": null,
        "RHGNR": null,
        "RHPSP": null,
        "RHESF": null,
        "RHFA": null,
        "RHINEM": null,
        "RHOutros": null,
        "NumeroOperacionaisTerrestresEnv": null,
        "Operacionais": 17,
        "NumeroOperacionaisAereosEnvolvi": null,
        "RTBombeiros": null,
        "RTFEPC": null,
        "RTUEPS": null,
        "RTGNR": null,
        "RTPSP": null,
        "RTESF": null,
        "RTFA": null,
        "RTINEM": null,
        "RTOutros": null,
        "NumeroMeiosTerrestresEnvolvidos": 5,
        "GruposReforco": null,
        "HELigeiro": null,
        "HEPesado": null,
        "HECoordenacao": null,
        "HEOutro": null,
        "AVMedio": null,
        "AVPesado": null,
        "AVReconhecimento": null,
        "AVOutro": null,
        "NumeroMeiosAereosEnvolvidos": 0,
        "Latitude": 41.16583,
        "Longitude": -8.6769800000000004,
        "DDD": null,
        "DMM": null,
        "DMS": null,
        "DataDosDados": 1768931120000,
        "Simbol": "21 - Em Conclusão",
        "Status": 0,
        "Obs": null,
        "NumeroMeiosAquaticos": 0
      }
    },
    {
      "type": "Feature",
      "id": 5664102,
      "geometry": {
        "type": "Point",
        "coordinates": [
          -9.2792739998023013,
          38.856640000298263
        ]
      },
      "properties": {
        "OBJECTID": 5664102,
        "ID_oc": 26614803,
        "Numero": 20260092816,
        "Ano": null,
        "DataInicioOcorrencia": "2026-01-20T16:51:00",
        "DataOcorrencia": 1768931460000,
        "Data": 1768927860000,
        "Hora": null,
        "Duracao": null,
        "DuracaoMinutos": null,
        "FaseIncendio": null,
        "GrupoOc": null,
        "GrupoOc_ID": null,
        "CodNatureza": 3111,
        "IDFamilia": null,
        "Familia": null,
        "IDEspecie": null,
        "Especie": null,
        "IDTipo": null,
        "Tipo": null,
        "Natureza": "Queima",
        "CodImportancia": null,
        "Importancia": null,
        "CodEstadoOcorrencia": null,
        "EstadoOcorrencia": "Conclusão",
        "EstadoAgrupado": "Em Conclusão",
        "CREPC_ID": null,
        "CSREPC": "Grande Lisboa",
        "CSREPC_ID": null,
        "CREPC": "Lisboa e Vale do Tejo",
        "DI": null,
        "Distrito": null,
        "NUT_III": null,
        "CIM": null,
        "DICO": null,
        "Concelho": "Sintra",
        "DICOFRE": null,
        "Freguesia": "Almargem do Bispo",
        "Localidade": "União das Freguesias de Almargem do Bispo, Pêro Pinheiro e Montelavar",
        "Endereco": null,
        "EntidadeResponsavel": null,
        "EntidadeGestora": null,
        "PCO": null,
        "COS": null,
        "UltimoPOSIT": null,
        "QuantEntidades": null,
        "RHBombeiros": null,
        "RHFEPC": null,
        "RHUEPS": null,
        "RHGNR": null,
        "RHPSP": null,
        "RHESF": null,
        "RHFA": null,
        "RHINEM": null,
        "RHOutros": null,
        "NumeroOperacionaisTerrestresEnv": null,
        "Operacionais": 7,
        "NumeroOperacionaisAereosEnvolvi": null,
        "RTBombeiros": null,
        "RTFEPC": null,
        "RTUEPS": null,
        "RTGNR": null,
        "RTPSP": null,
        "RTESF": null,
        "RTFA": null,
        "RTINEM": null,
        "RTOutros": null,
        "NumeroMeiosTerrestresEnvolvidos": 2,
        "GruposReforco": null,
        "HELigeiro": null,
        "HEPesado": null,
        "HECoordenacao": null,
        "HEOutro": null,
        "AVMedio": null,
        "AVPesado": null,
        "AVReconhecimento": null,
        "AVOutro": null,
        "NumeroMeiosAereosEnvolvidos": 0,
        "Latitude": 38.856639999999999,
        "Longitude": -9.2792739999999991,
        "DDD": null,
        "DMM": null,
        "DMS": null,
        "DataDosDados": 1768931120000,
        "Simbol": "31 - Em Conclusão",
        "Status": 0,
        "Obs": null,
        "NumeroMeiosAquaticos": 0
      }
    },
    {
      "type": "Feature",
      "id": 5664103,
      "geometry": {
        "type": "Point",
        "coordinates": [
          -6.9706280002357683,
          41.411219999609273
        ]
      },
      "properties": {
        "OBJECTID": 5664103,
        "ID_oc": 26614721,
        "Numero": 20260092734,
        "Ano": null,
        "DataInicioOcorrencia": "2026-01-20T16:31:00",
        "DataOcorrencia": 1768930260000,
        "Data": 1768926660000,
        "Hora": null,
        "Duracao": null,
        "DuracaoMinutos": null,
        "FaseIncendio": null,
        "GrupoOc": null,
        "GrupoOc_ID": null,
        "CodNatureza": 4331,
        "IDFamilia": null,
        "Familia": null,
        "IDEspecie": null,
        "Especie": null,
        "IDTipo": null,
        "Tipo": null,
        "Natureza": "Busca e Resgate Terrestre, de Animais",
        "CodImportancia": null,
        "Importancia": null,
        "CodEstadoOcorrencia": null,
        "EstadoOcorrencia": "Despacho de 1.º Alerta",
        "EstadoAgrupado": "Em Despacho",
        "CREPC_ID": null,
        "CSREPC": "Terras de Trás-os-Montes",
        "CSREPC_ID": null,
        "CREPC": "Norte",
        "DI": null,
        "Distrito": null,
        "NUT_III": null,
        "CIM": null,
        "DICO": null,
        "Concelho": "Alfândega da Fé",
        "DICOFRE": null,
        "Freguesia": "Sambade",
        "Localidade": "SAMBADE",
        "Endereco": null,
        "EntidadeResponsavel": null,
        "EntidadeGestora": null,
        "PCO": null,
        "COS": null,
        "UltimoPOSIT": null,
        "QuantEntidades": null,
        "RHBombeiros": null,
        "RHFEPC": null,
        "RHUEPS": null,
        "RHGNR": null,
        "RHPSP": null,
        "RHESF": null,
        "RHFA": null,
        "RHINEM": null,
        "RHOutros": null,
        "NumeroOperacionaisTerrestresEnv": null,
        "Operacionais": 2,
        "NumeroOperacionaisAereosEnvolvi": null,
        "RTBombeiros": null,
        "RTFEPC": null,
        "RTUEPS": null,
        "RTGNR": null,
        "RTPSP": null,
        "RTESF": null,
        "RTFA": null,
        "RTINEM": null,
        "RTOutros": null,
        "NumeroMeiosTerrestresEnvolvidos": 1,
        "GruposReforco": null,
        "HELigeiro": null,
        "HEPesado": null,
        "HECoordenacao": null,
        "HEOutro": null,
        "AVMedio": null,
        "AVPesado": null,
        "AVReconhecimento": null,
        "AVOutro": null,
        "NumeroMeiosAereosEnvolvidos": 0,
        "Latitude": 41.41122,
        "Longitude": -6.9706279999999996,
        "DDD": null,
        "DMM": null,
        "DMS": null,
        "DataDosDados": 1768931120000,
        "Simbol": "43 - Em Despacho",
        "Status": 0,
        "Obs": null,
        "NumeroMeiosAquaticos": 0
      }
    },
    {
      "type": "Feature",
      "id": 5664104,
      "geometry": {
        "type": "Point",
        "coordinates": [
          -8.2422099998574492,
          37.119669000186896
        ]
      },
      "properties": {
        "OBJECTID": 5664104,
        "ID_oc": 26615030,
        "Numero": 20260093043,
        "Ano": null,
        "DataInicioOcorrencia": "2026-01-20T17:35:00",
        "DataOcorrencia": 1768934100000,
        "Data": 1768930500000,
        "Hora": null,
        "Duracao": null,
        "DuracaoMinutos": null,
        "FaseIncendio": null,
        "GrupoOc": null,
        "GrupoOc_ID": null,
        "CodNatureza": 2407,
        "IDFamilia": null,
        "Familia": null,
        "IDEspecie": null,
        "Especie": null,
        "IDTipo": null,
        "Tipo": null,
        "Natureza": "Despiste",
        "CodImportancia": null,
        "Importancia": null,
        "CodEstadoOcorrencia": null,
        "EstadoOcorrencia": "Despacho de 1.º Alerta",
        "EstadoAgrupado": "Em Despacho",
        "CREPC_ID": null,
        "CSREPC": "Algarve",
        "CSREPC_ID": null,
        "CREPC": "Algarve",
        "DI": null,
        "Distrito": null,
        "NUT_III": null,
        "CIM": null,
        "DICO": null,
        "Concelho": "Albufeira",
        "DICOFRE": null,
        "Freguesia": "Ferreiras",
        "Localidade": "Ferreiras",
        "Endereco": null,
        "EntidadeResponsavel": null,
        "EntidadeGestora": null,
        "PCO": null,
        "COS": null,
        "UltimoPOSIT": null,
        "QuantEntidades": null,
        "RHBombeiros": null,
        "RHFEPC": null,
        "RHUEPS": null,
        "RHGNR": null,
        "RHPSP": null,
        "RHESF": null,
        "RHFA": null,
        "RHINEM": null,
        "RHOutros": null,
        "NumeroOperacionaisTerrestresEnv": null,
        "Operacionais": 5,
        "NumeroOperacionaisAereosEnvolvi": null,
        "RTBombeiros": null,
        "RTFEPC": null,
        "RTUEPS": null,
        "RTGNR": null,
        "RTPSP": null,
        "RTESF": null,
        "RTFA": null,
        "RTINEM": null,
        "RTOutros": null,
        "NumeroMeiosTerrestresEnvolvidos": 1,
        "GruposReforco": null,
        "HELigeiro": null,
        "HEPesado": null,
        "HECoordenacao": null,
        "HEOutro": null,
        "AVMedio": null,
        "AVPesado": null,
        "AVReconhecimento": null,
        "AVOutro": null,
        "NumeroMeiosAereosEnvolvidos": 0,
        "Latitude": 37.119669000000002,
        "Longitude": -8.24221,
        "DDD": null,
        "DMM": null,
        "DMS": null,
        "DataDosDados": 1768931120000,
        "Simbol": "24 - Em Despacho",
        "Status": 0,
        "Obs": null,
        "NumeroMeiosAquaticos": 0
      }
    },
    {
      "type": "Feature",
      "id": 5664105,
      "geometry": {
        "type": "Point",
        "coordinates": [
          -8.4442880005785792,
          39.62579300010875
        ]
      },
      "properties": {
        "OBJECTID": 5664105,
        "ID_oc": 26614237,
        "Numero": 20260092250,
        "Ano": null,
        "DataInicioOcorrencia": "2026-01-20T14:50:00",
        "DataOcorrencia": 1768924200000,
        "Data": 1768920600000,
        "Hora": null,
        "Duracao": null,
        "DuracaoMinutos": null,
        "FaseIncendio": null,
        "GrupoOc": null,
        "GrupoOc_ID": null,
        "CodNatureza": 2407,
        "IDFamilia": null,
        "Familia": null,
        "IDEspecie": null,
        "Especie": null,
        "IDTipo": null,
        "Tipo": null,
        "Natureza": "Despiste",
        "CodImportancia": null,
        "Importancia": null,
        "CodEstadoOcorrencia": null,
        "EstadoOcorrencia": "Conclusão",
        "EstadoAgrupado": "Em Conclusão",
        "CREPC_ID": null,
        "CSREPC": "Médio Tejo",
        "CSREPC_ID": null,
        "CREPC": "Lisboa e Vale do Tejo",
        "DI": null,
        "Distrito": null,
        "NUT_III": null,
        "CIM": null,
        "DICO": null,
        "Concelho": "Tomar",
        "DICOFRE": null,
        "Freguesia": "Carregueiros",
        "Localidade": "Carregueiros",
        "Endereco": null,
        "EntidadeResponsavel": null,
        "EntidadeGestora": null,
        "PCO": null,
        "COS": null,
        "UltimoPOSIT": null,
        "QuantEntidades": null,
        "RHBombeiros": null,
        "RHFEPC": null,
        "RHUEPS": null,
        "RHGNR": null,
        "RHPSP": null,
        "RHESF": null,
        "RHFA": null,
        "RHINEM": null,
        "RHOutros": null,
        "NumeroOperacionaisTerrestresEnv": null,
        "Operacionais": 4,
        "NumeroOperacionaisAereosEnvolvi": null,
        "RTBombeiros": null,
        "RTFEPC": null,
        "RTUEPS": null,
        "RTGNR": null,
        "RTPSP": null,
        "RTESF": null,
        "RTFA": null,
        "RTINEM": null,
        "RTOutros": null,
        "NumeroMeiosTerrestresEnvolvidos": 2,
        "GruposReforco": null,
        "HELigeiro": null,
        "HEPesado": null,
        "HECoordenacao": null,
        "HEOutro": null,
        "AVMedio": null,
        "AVPesado": null,
        "AVReconhecimento": null,
        "AVOutro": null,
        "NumeroMeiosAereosEnvolvidos": 0,
        "Latitude": 39.625793000000002,
        "Longitude": -8.4442880000000002,
        "DDD": null,
        "DMM": null,
        "DMS": null,
        "DataDosDados": 1768931120000,
        "Simbol": "24 - Em Conclusão",
        "Status": 0,
        "Obs": null,
        "NumeroMeiosAquaticos": 0
      }
    },
    {
      "type": "Feature",
      "id": 5664106,
      "geometry": {
        "type": "Point",
        "coordinates": [
          -8.9958299999381115,
          39.224613000039753
        ]
      },
      "properties": {
        "OBJECTID": 5664106,
        "ID_oc": 26614514,
        "Numero": 20260092527,
        "Ano": null,
        "DataInicioOcorrencia": "2026-01-20T15:38:00",
        "DataOcorrencia": 1768927080000,
        "Data": 1768923480000,
        "Hora": null,
        "Duracao": null,
        "DuracaoMinutos": null,
        "FaseIncendio": null,
        "GrupoOc": null,
        "GrupoOc_ID": null,
        "CodNatureza": 2407,
        "IDFamilia": null,
        "Familia": null,
        "IDEspecie": null,
        "Especie": null,
        "IDTipo": null,
        "Tipo": null,
        "Natureza": "Despiste",
        "CodImportancia": null,
        "Importancia": null,
        "CodEstadoOcorrencia": null,
        "EstadoOcorrencia": "Conclusão",
        "EstadoAgrupado": "Em Conclusão",
        "CREPC_ID": null,
        "CSREPC": "Oeste",
        "CSREPC_ID": null,
        "CREPC": "Lisboa e Vale do Tejo",
        "DI": null,
        "Distrito": null,
        "NUT_III": null,
        "CIM": null,
        "DICO": null,
        "Concelho": "Cadaval",
        "DICOFRE": null,
        "Freguesia": "Lamas e Cercal",
        "Localidade": "CERCAL",
        "Endereco": null,
        "EntidadeResponsavel": null,
        "EntidadeGestora": null,
        "PCO": null,
        "COS": null,
        "UltimoPOSIT": null,
        "QuantEntidades": null,
        "RHBombeiros": null,
        "RHFEPC": null,
        "RHUEPS": null,
        "RHGNR": null,
        "RHPSP": null,
        "RHESF": null,
        "RHFA": null,
        "RHINEM": null,
        "RHOutros": null,
        "NumeroOperacionaisTerrestresEnv": null,
        "Operacionais": 8,
        "NumeroOperacionaisAereosEnvolvi": null,
        "RTBombeiros": null,
        "RTFEPC": null,
        "RTUEPS": null,
        "RTGNR": null,
        "RTPSP": null,
        "RTESF": null,
        "RTFA": null,
        "RTINEM": null,
        "RTOutros": null,
        "NumeroMeiosTerrestresEnvolvidos": 4,
        "GruposReforco": null,
        "HELigeiro": null,
        "HEPesado": null,
        "HECoordenacao": null,
        "HEOutro": null,
        "AVMedio": null,
        "AVPesado": null,
        "AVReconhecimento": null,
        "AVOutro": null,
        "NumeroMeiosAereosEnvolvidos": 0,
        "Latitude": 39.224612999999998,
        "Longitude": -8.9958299999999998,
        "DDD": null,
        "DMM": null,
        "DMS": null,
        "DataDosDados": 1768931120000,
        "Simbol": "24 - Em Conclusão",
        "Status": 0,
        "Obs": null,
        "NumeroMeiosAquaticos": 0
      }
    },
    {
      "type": "Feature",
      "id": 5664107,
      "geometry": {
        "type": "Point",
        "coordinates": [
          -8.8654550001853742,
          39.602895000300656
        ]
      },
      "properties": {
        "OBJECTID": 5664107,
        "ID_oc": 26614807,
        "Numero": 20260092820,
        "Ano": null,
        "DataInicioOcorrencia": "2026-01-20T16:47:00",
        "DataOcorrencia": 1768931220000,
        "Data": 1768927620000,
        "Hora": null,
        "Duracao": null,
        "DuracaoMinutos": null,
        "FaseIncendio": null,
        "GrupoOc": null,
        "GrupoOc_ID": null,
        "CodNatureza": 2403,
        "IDFamilia": null,
        "Familia": null,
        "IDEspecie": null,
        "Especie": null,
        "IDTipo": null,
        "Tipo": null,
        "Natureza": "Colisão rodoviária",
        "CodImportancia": null,
        "Importancia": null,
        "CodEstadoOcorrencia": null,
        "EstadoOcorrencia": "Em Resolução",
        "EstadoAgrupado": "Em Resolução",
        "CREPC_ID": null,
        "CSREPC": "Região de Leiria",
        "CSREPC_ID": null,
        "CREPC": "Centro",
        "DI": null,
        "Distrito": null,
        "NUT_III": null,
        "CIM": null,
        "DICO": null,
        "Concelho": "Porto de Mós",
        "DICOFRE": null,
        "Freguesia": "Pedreiras",
        "Localidade": "Tremoceira",
        "Endereco": null,
        "EntidadeResponsavel": null,
        "EntidadeGestora": null,
        "PCO": null,
        "COS": null,
        "UltimoPOSIT": null,
        "QuantEntidades": null,
        "RHBombeiros": null,
        "RHFEPC": null,
        "RHUEPS": null,
        "RHGNR": null,
        "RHPSP": null,
        "RHESF": null,
        "RHFA": null,
        "RHINEM": null,
        "RHOutros": null,
        "NumeroOperacionaisTerrestresEnv": null,
        "Operacionais": 13,
        "NumeroOperacionaisAereosEnvolvi": null,
        "RTBombeiros": null,
        "RTFEPC": null,
        "RTUEPS": null,
        "RTGNR": null,
        "RTPSP": null,
        "RTESF": null,
        "RTFA": null,
        "RTINEM": null,
        "RTOutros": null,
        "NumeroMeiosTerrestresEnvolvidos": 5,
        "GruposReforco": null,
        "HELigeiro": null,
        "HEPesado": null,
        "HECoordenacao": null,
        "HEOutro": null,
        "AVMedio": null,
        "AVPesado": null,
        "AVReconhecimento": null,
        "AVOutro": null,
        "NumeroMeiosAereosEnvolvidos": 0,
        "Latitude": 39.602894999999997,
        "Longitude": -8.8654550000000008,
        "DDD": null,
        "DMM": null,
        "DMS": null,
        "DataDosDados": 1768931120000,
        "Simbol": "24 - Em Resolução",
        "Status": 0,
        "Obs": null,
        "NumeroMeiosAquaticos": 0
      }
    },
    {
      "type": "Feature",
      "id": 5664108,
      "geometry": {
        "type": "Point",
        "coordinates": [
          -7.9420319994899753,
          37.018650000372503
        ]
      },
      "properties": {
        "OBJECTID": 5664108,
        "ID_oc": 26614925,
        "Numero": 20260092938,
        "Ano": null,
        "DataInicioOcorrencia": "2026-01-20T17:21:00",
        "DataOcorrencia": 1768933260000,
        "Data": 1768929660000,
        "Hora": null,
        "Duracao": null,
        "DuracaoMinutos": null,
        "FaseIncendio": null,
        "GrupoOc": null,
        "GrupoOc_ID": null,
        "CodNatureza": 3201,
        "IDFamilia": null,
        "Familia": null,
        "IDEspecie": null,
        "Especie": null,
        "IDTipo": null,
        "Tipo": null,
        "Natureza": "Detritos não confinados",
        "CodImportancia": null,
        "Importancia": null,
        "CodEstadoOcorrencia": null,
        "EstadoOcorrencia": "Em Resolução",
        "EstadoAgrupado": "Em Resolução",
        "CREPC_ID": null,
        "CSREPC": "Algarve",
        "CSREPC_ID": null,
        "CREPC": "Algarve",
        "DI": null,
        "Distrito": null,
        "NUT_III": null,
        "CIM": null,
        "DICO": null,
        "Concelho": "Faro",
        "DICOFRE": null,
        "Freguesia": "Faro (Sé e São Pedro)",
        "Localidade": "Faro",
        "Endereco": null,
        "EntidadeResponsavel": null,
        "EntidadeGestora": null,
        "PCO": null,
        "COS": null,
        "UltimoPOSIT": null,
        "QuantEntidades": null,
        "RHBombeiros": null,
        "RHFEPC": null,
        "RHUEPS": null,
        "RHGNR": null,
        "RHPSP": null,
        "RHESF": null,
        "RHFA": null,
        "RHINEM": null,
        "RHOutros": null,
        "NumeroOperacionaisTerrestresEnv": null,
        "Operacionais": 8,
        "NumeroOperacionaisAereosEnvolvi": null,
        "RTBombeiros": null,
        "RTFEPC": null,
        "RTUEPS": null,
        "RTGNR": null,
        "RTPSP": null,
        "RTESF": null,
        "RTFA": null,
        "RTINEM": null,
        "RTOutros": null,
        "NumeroMeiosTerrestresEnvolvidos": 3,
        "GruposReforco": null,
        "HELigeiro": null,
        "HEPesado": null,
        "HECoordenacao": null,
        "HEOutro": null,
        "AVMedio": null,
        "AVPesado": null,
        "AVReconhecimento": null,
        "AVOutro": null,
        "NumeroMeiosAereosEnvolvidos": 0,
        "Latitude": 37.018650000000001,
        "Longitude": -7.9420320000000002,
        "DDD": null,
        "DMM": null,
        "DMS": null,
        "DataDosDados": 1768931120000,
        "Simbol": "32 - Em Resolução",
        "Status": 0,
        "Obs": null,
        "NumeroMeiosAquaticos": 0
      }
    },
    {
      "type": "Feature",
      "id": 5664109,
      "geometry": {
        "type": "Point",
        "coordinates": [
          -8.2977800000774291,
          40.282219999750048
        ]
      },
      "properties": {
        "OBJECTID": 5664109,
        "ID_oc": 26614497,
        "Numero": 20260092510,
        "Ano": null,
        "DataInicioOcorrencia": "2026-01-20T15:43:00",
        "DataOcorrencia": 1768927380000,
        "Data": 1768923780000,
        "Hora": null,
        "Duracao": null,
        "DuracaoMinutos": null,
        "FaseIncendio": null,
        "GrupoOc": null,
        "GrupoOc_ID": null,
        "CodNatureza": 2403,
        "IDFamilia": null,
        "Familia": null,
        "IDEspecie": null,
        "Especie": null,
        "IDTipo": null,
        "Tipo": null,
        "Natureza": "Colisão rodoviária",
        "CodImportancia": null,
        "Importancia": null,
        "CodEstadoOcorrencia": null,
        "EstadoOcorrencia": "Conclusão",
        "EstadoAgrupado": "Em Conclusão",
        "CREPC_ID": null,
        "CSREPC": "Região de Coimbra",
        "CSREPC_ID": null,
        "CREPC": "Centro",
        "DI": null,
        "Distrito": null,
        "NUT_III": null,
        "CIM": null,
        "DICO": null,
        "Concelho": "Penacova",
        "DICOFRE": null,
        "Freguesia": "Penacova",
        "Localidade": "IP3 Km59.5 Viseu»»CBR",
        "Endereco": null,
        "EntidadeResponsavel": null,
        "EntidadeGestora": null,
        "PCO": null,
        "COS": null,
        "UltimoPOSIT": null,
        "QuantEntidades": null,
        "RHBombeiros": null,
        "RHFEPC": null,
        "RHUEPS": null,
        "RHGNR": null,
        "RHPSP": null,
        "RHESF": null,
        "RHFA": null,
        "RHINEM": null,
        "RHOutros": null,
        "NumeroOperacionaisTerrestresEnv": null,
        "Operacionais": 8,
        "NumeroOperacionaisAereosEnvolvi": null,
        "RTBombeiros": null,
        "RTFEPC": null,
        "RTUEPS": null,
        "RTGNR": null,
        "RTPSP": null,
        "RTESF": null,
        "RTFA": null,
        "RTINEM": null,
        "RTOutros": null,
        "NumeroMeiosTerrestresEnvolvidos": 3,
        "GruposReforco": null,
        "HELigeiro": null,
        "HEPesado": null,
        "HECoordenacao": null,
        "HEOutro": null,
        "AVMedio": null,
        "AVPesado": null,
        "AVReconhecimento": null,
        "AVOutro": null,
        "NumeroMeiosAereosEnvolvidos": 0,
        "Latitude": 40.282220000000002,
        "Longitude": -8.2977799999999995,
        "DDD": null,
        "DMM": null,
        "DMS": null,
        "DataDosDados": 1768931120000,
        "Simbol": "24 - Em Conclusão",
        "Status": 0,
        "Obs": null,
        "NumeroMeiosAquaticos": 0
      }
    },
    {
      "type": "Feature",
      "id": 5664110,
      "geometry": {
        "type": "Point",
        "coordinates": [
          -8.7400400000432619,
          39.640545999998011
        ]
      },
      "properties": {
        "OBJECTID": 5664110,
        "ID_oc": 26614922,
        "Numero": 20260092935,
        "Ano": null,
        "DataInicioOcorrencia": "2026-01-20T17:16:00",
        "DataOcorrencia": 1768932960000,
        "Data": 1768929360000,
        "Hora": null,
        "Duracao": null,
        "DuracaoMinutos": null,
        "FaseIncendio": null,
        "GrupoOc": null,
        "GrupoOc_ID": null,
        "CodNatureza": 2407,
        "IDFamilia": null,
        "Familia": null,
        "IDEspecie": null,
        "Especie": null,
        "IDTipo": null,
        "Tipo": null,
        "Natureza": "Despiste",
        "CodImportancia": null,
        "Importancia": null,
        "CodEstadoOcorrencia": null,
        "EstadoOcorrencia": "Em Curso",
        "EstadoAgrupado": "Em Curso",
        "CREPC_ID": null,
        "CSREPC": "Região de Leiria",
        "CSREPC_ID": null,
        "CREPC": "Centro",
        "DI": null,
        "Distrito": null,
        "NUT_III": null,
        "CIM": null,
        "DICO": null,
        "Concelho": "Batalha",
        "DICOFRE": null,
        "Freguesia": "São Mamede",
        "Localidade": "Vale da Seta",
        "Endereco": null,
        "EntidadeResponsavel": null,
        "EntidadeGestora": null,
        "PCO": null,
        "COS": null,
        "UltimoPOSIT": null,
        "QuantEntidades": null,
        "RHBombeiros": null,
        "RHFEPC": null,
        "RHUEPS": null,
        "RHGNR": null,
        "RHPSP": null,
        "RHESF": null,
        "RHFA": null,
        "RHINEM": null,
        "RHOutros": null,
        "NumeroOperacionaisTerrestresEnv": null,
        "Operacionais": 9,
        "NumeroOperacionaisAereosEnvolvi": null,
        "RTBombeiros": null,
        "RTFEPC": null,
        "RTUEPS": null,
        "RTGNR": null,
        "RTPSP": null,
        "RTESF": null,
        "RTFA": null,
        "RTINEM": null,
        "RTOutros": null,
        "NumeroMeiosTerrestresEnvolvidos": 3,
        "GruposReforco": null,
        "HELigeiro": null,
        "HEPesado": null,
        "HECoordenacao": null,
        "HEOutro": null,
        "AVMedio": null,
        "AVPesado": null,
        "AVReconhecimento": null,
        "AVOutro": null,
        "NumeroMeiosAereosEnvolvidos": 0,
        "Latitude": 39.640546000000001,
        "Longitude": -8.7400400000000005,
        "DDD": null,
        "DMM": null,
        "DMS": null,
        "DataDosDados": 1768931120000,
        "Simbol": "24 - Em Curso",
        "Status": 0,
        "Obs": null,
        "NumeroMeiosAquaticos": 0
      }
    },
    {
      "type": "Feature",
      "id": 5664111,
      "geometry": {
        "type": "Point",
        "coordinates": [
          -9.2974509997329324,
          38.765314999614745
        ]
      },
      "properties": {
        "OBJECTID": 5664111,
        "ID_oc": 26614765,
        "Numero": 20260092778,
        "Ano": null,
        "DataInicioOcorrencia": "2026-01-20T16:34:00",
        "DataOcorrencia": 1768930440000,
        "Data": 1768926840000,
        "Hora": null,
        "Duracao": null,
        "DuracaoMinutos": null,
        "FaseIncendio": null,
        "GrupoOc": null,
        "GrupoOc_ID": null,
        "CodNatureza": 2401,
        "IDFamilia": null,
        "Familia": null,
        "IDEspecie": null,
        "Especie": null,
        "IDTipo": null,
        "Tipo": null,
        "Natureza": "Atropelamento rodoviário",
        "CodImportancia": null,
        "Importancia": null,
        "CodEstadoOcorrencia": null,
        "EstadoOcorrencia": "Conclusão",
        "EstadoAgrupado": "Em Conclusão",
        "CREPC_ID": null,
        "CSREPC": "Grande Lisboa",
        "CSREPC_ID": null,
        "CREPC": "Lisboa e Vale do Tejo",
        "DI": null,
        "Distrito": null,
        "NUT_III": null,
        "CIM": null,
        "DICO": null,
        "Concelho": "Sintra",
        "DICOFRE": null,
        "Freguesia": "Agualva e Mira-Sintra",
        "Localidade": "Cacém",
        "Endereco": null,
        "EntidadeResponsavel": null,
        "EntidadeGestora": null,
        "PCO": null,
        "COS": null,
        "UltimoPOSIT": null,
        "QuantEntidades": null,
        "RHBombeiros": null,
        "RHFEPC": null,
        "RHUEPS": null,
        "RHGNR": null,
        "RHPSP": null,
        "RHESF": null,
        "RHFA": null,
        "RHINEM": null,
        "RHOutros": null,
        "NumeroOperacionaisTerrestresEnv": null,
        "Operacionais": 2,
        "NumeroOperacionaisAereosEnvolvi": null,
        "RTBombeiros": null,
        "RTFEPC": null,
        "RTUEPS": null,
        "RTGNR": null,
        "RTPSP": null,
        "RTESF": null,
        "RTFA": null,
        "RTINEM": null,
        "RTOutros": null,
        "NumeroMeiosTerrestresEnvolvidos": 1,
        "GruposReforco": null,
        "HELigeiro": null,
        "HEPesado": null,
        "HECoordenacao": null,
        "HEOutro": null,
        "AVMedio": null,
        "AVPesado": null,
        "AVReconhecimento": null,
        "AVOutro": null,
        "NumeroMeiosAereosEnvolvidos": 0,
        "Latitude": 38.765315000000001,
        "Longitude": -9.2974510000000006,
        "DDD": null,
        "DMM": null,
        "DMS": null,
        "DataDosDados": 1768931120000,
        "Simbol": "24 - Em Conclusão",
        "Status": 0,
        "Obs": null,
        "NumeroMeiosAquaticos": 0
      }
    },
    {
      "type": "Feature",
      "id": 5664112,
      "geometry": {
        "type": "Point",
        "coordinates": [
          -8.6449529997639036,
          41.152972999849801
        ]
      },
      "properties": {
        "OBJECTID": 5664112,
        "ID_oc": 26614756,
        "Numero": 20260092769,
        "Ano": null,
        "DataInicioOcorrencia": "2026-01-20T16:34:00",
        "DataOcorrencia": 1768930440000,
        "Data": 1768926840000,
        "Hora": null,
        "Duracao": null,
        "DuracaoMinutos": null,
        "FaseIncendio": null,
        "GrupoOc": null,
        "GrupoOc_ID": null,
        "CodNatureza": 2403,
        "IDFamilia": null,
        "Familia": null,
        "IDEspecie": null,
        "Especie": null,
        "IDTipo": null,
        "Tipo": null,
        "Natureza": "Colisão rodoviária",
        "CodImportancia": null,
        "Importancia": null,
        "CodEstadoOcorrencia": null,
        "EstadoOcorrencia": "Em Resolução",
        "EstadoAgrupado": "Em Resolução",
        "CREPC_ID": null,
        "CSREPC": "Area M. Porto",
        "CSREPC_ID": null,
        "CREPC": "Norte",
        "DI": null,
        "Distrito": null,
        "NUT_III": null,
        "CIM": null,
        "DICO": null,
        "Concelho": "Porto",
        "DICOFRE": null,
        "Freguesia": "Lordelo do Ouro e Massarelos",
        "Localidade": null,
        "Endereco": null,
        "EntidadeResponsavel": null,
        "EntidadeGestora": null,
        "PCO": null,
        "COS": null,
        "UltimoPOSIT": null,
        "QuantEntidades": null,
        "RHBombeiros": null,
        "RHFEPC": null,
        "RHUEPS": null,
        "RHGNR": null,
        "RHPSP": null,
        "RHESF": null,
        "RHFA": null,
        "RHINEM": null,
        "RHOutros": null,
        "NumeroOperacionaisTerrestresEnv": null,
        "Operacionais": 5,
        "NumeroOperacionaisAereosEnvolvi": null,
        "RTBombeiros": null,
        "RTFEPC": null,
        "RTUEPS": null,
        "RTGNR": null,
        "RTPSP": null,
        "RTESF": null,
        "RTFA": null,
        "RTINEM": null,
        "RTOutros": null,
        "NumeroMeiosTerrestresEnvolvidos": 3,
        "GruposReforco": null,
        "HELigeiro": null,
        "HEPesado": null,
        "HECoordenacao": null,
        "HEOutro": null,
        "AVMedio": null,
        "AVPesado": null,
        "AVReconhecimento": null,
        "AVOutro": null,
        "NumeroMeiosAereosEnvolvidos": 0,
        "Latitude": 41.152973000000003,
        "Longitude": -8.6449529999999992,
        "DDD": null,
        "DMM": null,
        "DMS": null,
        "DataDosDados": 1768931120000,
        "Simbol": "24 - Em Resolução",
        "Status": 0,
        "Obs": null,
        "NumeroMeiosAquaticos": 0
      }
    },
    {
      "type": "Feature",
      "id": 5664113,
      "geometry": {
        "type": "Point",
        "coordinates": [
          -8.5794520003294288,
          41.027836999855055
        ]
      },
      "properties": {
        "OBJECTID": 5664113,
        "ID_oc": 26614940,
        "Numero": 20260092953,
        "Ano": null,
        "DataInicioOcorrencia": "2026-01-20T17:20:00",
        "DataOcorrencia": 1768933200000,
        "Data": 1768929600000,
        "Hora": null,
        "Duracao": null,
        "DuracaoMinutos": null,
        "FaseIncendio": null,
        "GrupoOc": null,
        "GrupoOc_ID": null,
        "CodNatureza": 2403,
        "IDFamilia": null,
        "Familia": null,
        "IDEspecie": null,
        "Especie": null,
        "IDTipo": null,
        "Tipo": null,
        "Natureza": "Colisão rodoviária",
        "CodImportancia": null,
        "Importancia": null,
        "CodEstadoOcorrencia": null,
        "EstadoOcorrencia": "Conclusão",
        "EstadoAgrupado": "Em Conclusão",
        "CREPC_ID": null,
        "CSREPC": "Area M. Porto",
        "CSREPC_ID": null,
        "CREPC": "Norte",
        "DI": null,
        "Distrito": null,
        "NUT_III": null,
        "CIM": null,
        "DICO": null,
        "Concelho": "Vila Nova de Gaia",
        "DICOFRE": null,
        "Freguesia": "Grijó",
        "Localidade": null,
        "Endereco": null,
        "EntidadeResponsavel": null,
        "EntidadeGestora": null,
        "PCO": null,
        "COS": null,
        "UltimoPOSIT": null,
        "QuantEntidades": null,
        "RHBombeiros": null,
        "RHFEPC": null,
        "RHUEPS": null,
        "RHGNR": null,
        "RHPSP": null,
        "RHESF": null,
        "RHFA": null,
        "RHINEM": null,
        "RHOutros": null,
        "NumeroOperacionaisTerrestresEnv": null,
        "Operacionais": 7,
        "NumeroOperacionaisAereosEnvolvi": null,
        "RTBombeiros": null,
        "RTFEPC": null,
        "RTUEPS": null,
        "RTGNR": null,
        "RTPSP": null,
        "RTESF": null,
        "RTFA": null,
        "RTINEM": null,
        "RTOutros": null,
        "NumeroMeiosTerrestresEnvolvidos": 2,
        "GruposReforco": null,
        "HELigeiro": null,
        "HEPesado": null,
        "HECoordenacao": null,
        "HEOutro": null,
        "AVMedio": null,
        "AVPesado": null,
        "AVReconhecimento": null,
        "AVOutro": null,
        "NumeroMeiosAereosEnvolvidos": 0,
        "Latitude": 41.027836999999998,
        "Longitude": -8.5794519999999999,
        "DDD": null,
        "DMM": null,
        "DMS": null,
        "DataDosDados": 1768931120000,
        "Simbol": "24 - Em Conclusão",
        "Status": 0,
        "Obs": null,
        "NumeroMeiosAquaticos": 0
      }
    },
    {
      "type": "Feature",
      "id": 5664114,
      "geometry": {
        "type": "Point",
        "coordinates": [
          -8.652913000409022,
          39.087718000235142
        ]
      },
      "properties": {
        "OBJECTID": 5664114,
        "ID_oc": 26614749,
        "Numero": 20260092762,
        "Ano": null,
        "DataInicioOcorrencia": "2026-01-20T16:39:00",
        "DataOcorrencia": 1768930740000,
        "Data": 1768927140000,
        "Hora": null,
        "Duracao": null,
        "DuracaoMinutos": null,
        "FaseIncendio": null,
        "GrupoOc": null,
        "GrupoOc_ID": null,
        "CodNatureza": 2403,
        "IDFamilia": null,
        "Familia": null,
        "IDEspecie": null,
        "Especie": null,
        "IDTipo": null,
        "Tipo": null,
        "Natureza": "Colisão rodoviária",
        "CodImportancia": null,
        "Importancia": null,
        "CodEstadoOcorrencia": null,
        "EstadoOcorrencia": "Em Resolução",
        "EstadoAgrupado": "Em Resolução",
        "CREPC_ID": null,
        "CSREPC": "Lezíria do Tejo",
        "CSREPC_ID": null,
        "CREPC": "Lisboa e Vale do Tejo",
        "DI": null,
        "Distrito": null,
        "NUT_III": null,
        "CIM": null,
        "DICO": null,
        "Concelho": "Salvaterra de Magos",
        "DICOFRE": null,
        "Freguesia": "Granho",
        "Localidade": "Granho",
        "Endereco": null,
        "EntidadeResponsavel": null,
        "EntidadeGestora": null,
        "PCO": null,
        "COS": null,
        "UltimoPOSIT": null,
        "QuantEntidades": null,
        "RHBombeiros": null,
        "RHFEPC": null,
        "RHUEPS": null,
        "RHGNR": null,
        "RHPSP": null,
        "RHESF": null,
        "RHFA": null,
        "RHINEM": null,
        "RHOutros": null,
        "NumeroOperacionaisTerrestresEnv": null,
        "Operacionais": 14,
        "NumeroOperacionaisAereosEnvolvi": null,
        "RTBombeiros": null,
        "RTFEPC": null,
        "RTUEPS": null,
        "RTGNR": null,
        "RTPSP": null,
        "RTESF": null,
        "RTFA": null,
        "RTINEM": null,
        "RTOutros": null,
        "NumeroMeiosTerrestresEnvolvidos": 6,
        "GruposReforco": null,
        "HELigeiro": null,
        "HEPesado": null,
        "HECoordenacao": null,
        "HEOutro": null,
        "AVMedio": null,
        "AVPesado": null,
        "AVReconhecimento": null,
        "AVOutro": null,
        "NumeroMeiosAereosEnvolvidos": 0,
        "Latitude": 39.087718000000002,
        "Longitude": -8.6529129999999999,
        "DDD": null,
        "DMM": null,
        "DMS": null,
        "DataDosDados": 1768931120000,
        "Simbol": "24 - Em Resolução",
        "Status": 0,
        "Obs": null,
        "NumeroMeiosAquaticos": 0
      }
    },
    {
      "type": "Feature",
      "id": 5664115,
      "geometry": {
        "type": "Point",
        "coordinates": [
          -8.528997000251044,
          40.443375000376392
        ]
      },
      "properties": {
        "OBJECTID": 5664115,
        "ID_oc": 26614524,
        "Numero": 20260092537,
        "Ano": null,
        "DataInicioOcorrencia": "2026-01-20T15:40:00",
        "DataOcorrencia": 1768927200000,
        "Data": 1768923600000,
        "Hora": null,
        "Duracao": null,
        "DuracaoMinutos": null,
        "FaseIncendio": null,
        "GrupoOc": null,
        "GrupoOc_ID": null,
        "CodNatureza": 2403,
        "IDFamilia": null,
        "Familia": null,
        "IDEspecie": null,
        "Especie": null,
        "IDTipo": null,
        "Tipo": null,
        "Natureza": "Colisão rodoviária",
        "CodImportancia": null,
        "Importancia": null,
        "CodEstadoOcorrencia": null,
        "EstadoOcorrencia": "Em Resolução",
        "EstadoAgrupado": "Em Resolução",
        "CREPC_ID": null,
        "CSREPC": "Região de Aveiro",
        "CSREPC_ID": null,
        "CREPC": "Centro",
        "DI": null,
        "Distrito": null,
        "NUT_III": null,
        "CIM": null,
        "DICO": null,
        "Concelho": "Anadia",
        "DICOFRE": null,
        "Freguesia": "São Lourenço do Bairro",
        "Localidade": "Couvelha",
        "Endereco": null,
        "EntidadeResponsavel": null,
        "EntidadeGestora": null,
        "PCO": null,
        "COS": null,
        "UltimoPOSIT": null,
        "QuantEntidades": null,
        "RHBombeiros": null,
        "RHFEPC": null,
        "RHUEPS": null,
        "RHGNR": null,
        "RHPSP": null,
        "RHESF": null,
        "RHFA": null,
        "RHINEM": null,
        "RHOutros": null,
        "NumeroOperacionaisTerrestresEnv": null,
        "Operacionais": 12,
        "NumeroOperacionaisAereosEnvolvi": null,
        "RTBombeiros": null,
        "RTFEPC": null,
        "RTUEPS": null,
        "RTGNR": null,
        "RTPSP": null,
        "RTESF": null,
        "RTFA": null,
        "RTINEM": null,
        "RTOutros": null,
        "NumeroMeiosTerrestresEnvolvidos": 5,
        "GruposReforco": null,
        "HELigeiro": null,
        "HEPesado": null,
        "HECoordenacao": null,
        "HEOutro": null,
        "AVMedio": null,
        "AVPesado": null,
        "AVReconhecimento": null,
        "AVOutro": null,
        "NumeroMeiosAereosEnvolvidos": 0,
        "Latitude": 40.443375000000003,
        "Longitude": -8.5289970000000004,
        "DDD": null,
        "DMM": null,
        "DMS": null,
        "DataDosDados": 1768931120000,
        "Simbol": "24 - Em Resolução",
        "Status": 0,
        "Obs": null,
        "NumeroMeiosAquaticos": 0
      }
    },
    {
      "type": "Feature",
      "id": 5664116,
      "geometry": {
        "type": "Point",
        "coordinates": [
          -9.2478969998168896,
          38.703909999586806
        ]
      },
      "properties": {
        "OBJECTID": 5664116,
        "ID_oc": 26613879,
        "Numero": 20260091892,
        "Ano": null,
        "DataInicioOcorrencia": "2026-01-20T13:51:00",
        "DataOcorrencia": 1768920660000,
        "Data": 1768917060000,
        "Hora": null,
        "Duracao": null,
        "DuracaoMinutos": null,
        "FaseIncendio": null,
        "GrupoOc": null,
        "GrupoOc_ID": null,
        "CodNatureza": 3321,
        "IDFamilia": null,
        "Familia": null,
        "IDEspecie": null,
        "Especie": null,
        "IDTipo": null,
        "Tipo": null,
        "Natureza": "Dano ou Queda de redes de fornecimento eléctrico",
        "CodImportancia": null,
        "Importancia": null,
        "CodEstadoOcorrencia": null,
        "EstadoOcorrencia": "Conclusão",
        "EstadoAgrupado": "Em Conclusão",
        "CREPC_ID": null,
        "CSREPC": "Grande Lisboa",
        "CSREPC_ID": null,
        "CREPC": "Lisboa e Vale do Tejo",
        "DI": null,
        "Distrito": null,
        "NUT_III": null,
        "CIM": null,
        "DICO": null,
        "Concelho": "Oeiras",
        "DICOFRE": null,
        "Freguesia": "Algés, Linda-a-Velha e Cruz Quebrada-Dafundo",
        "Localidade": "Linda a Velha",
        "Endereco": null,
        "EntidadeResponsavel": null,
        "EntidadeGestora": null,
        "PCO": null,
        "COS": null,
        "UltimoPOSIT": null,
        "QuantEntidades": null,
        "RHBombeiros": null,
        "RHFEPC": null,
        "RHUEPS": null,
        "RHGNR": null,
        "RHPSP": null,
        "RHESF": null,
        "RHFA": null,
        "RHINEM": null,
        "RHOutros": null,
        "NumeroOperacionaisTerrestresEnv": null,
        "Operacionais": 4,
        "NumeroOperacionaisAereosEnvolvi": null,
        "RTBombeiros": null,
        "RTFEPC": null,
        "RTUEPS": null,
        "RTGNR": null,
        "RTPSP": null,
        "RTESF": null,
        "RTFA": null,
        "RTINEM": null,
        "RTOutros": null,
        "NumeroMeiosTerrestresEnvolvidos": 1,
        "GruposReforco": null,
        "HELigeiro": null,
        "HEPesado": null,
        "HECoordenacao": null,
        "HEOutro": null,
        "AVMedio": null,
        "AVPesado": null,
        "AVReconhecimento": null,
        "AVOutro": null,
        "NumeroMeiosAereosEnvolvidos": 0,
        "Latitude": 38.70391,
        "Longitude": -9.247897,
        "DDD": null,
        "DMM": null,
        "DMS": null,
        "DataDosDados": 1768931120000,
        "Simbol": "33 - Em Conclusão",
        "Status": 0,
        "Obs": null,
        "NumeroMeiosAquaticos": 0
      }
    },
    {
      "type": "Feature",
      "id": 5664117,
      "geometry": {
        "type": "Point",
        "coordinates": [
          -8.5115309995555108,
          41.155311000402705
        ]
      },
      "properties": {
        "OBJECTID": 5664117,
        "ID_oc": 26614888,
        "Numero": 20260092901,
        "Ano": null,
        "DataInicioOcorrencia": "2026-01-20T17:03:00",
        "DataOcorrencia": 1768932180000,
        "Data": 1768928580000,
        "Hora": null,
        "Duracao": null,
        "DuracaoMinutos": null,
        "FaseIncendio": null,
        "GrupoOc": null,
        "GrupoOc_ID": null,
        "CodNatureza": 2403,
        "IDFamilia": null,
        "Familia": null,
        "IDEspecie": null,
        "Especie": null,
        "IDTipo": null,
        "Tipo": null,
        "Natureza": "Colisão rodoviária",
        "CodImportancia": null,
        "Importancia": null,
        "CodEstadoOcorrencia": null,
        "EstadoOcorrencia": "Chegada ao TO",
        "EstadoAgrupado": "Em Despacho",
        "CREPC_ID": null,
        "CSREPC": "Area M. Porto",
        "CSREPC_ID": null,
        "CREPC": "Norte",
        "DI": null,
        "Distrito": null,
        "NUT_III": null,
        "CIM": null,
        "DICO": null,
        "Concelho": "Gondomar",
        "DICOFRE": null,
        "Freguesia": "Fânzeres e São Pedro da Cova",
        "Localidade": null,
        "Endereco": null,
        "EntidadeResponsavel": null,
        "EntidadeGestora": null,
        "PCO": null,
        "COS": null,
        "UltimoPOSIT": null,
        "QuantEntidades": null,
        "RHBombeiros": null,
        "RHFEPC": null,
        "RHUEPS": null,
        "RHGNR": null,
        "RHPSP": null,
        "RHESF": null,
        "RHFA": null,
        "RHINEM": null,
        "RHOutros": null,
        "NumeroOperacionaisTerrestresEnv": null,
        "Operacionais": 2,
        "NumeroOperacionaisAereosEnvolvi": null,
        "RTBombeiros": null,
        "RTFEPC": null,
        "RTUEPS": null,
        "RTGNR": null,
        "RTPSP": null,
        "RTESF": null,
        "RTFA": null,
        "RTINEM": null,
        "RTOutros": null,
        "NumeroMeiosTerrestresEnvolvidos": 1,
        "GruposReforco": null,
        "HELigeiro": null,
        "HEPesado": null,
        "HECoordenacao": null,
        "HEOutro": null,
        "AVMedio": null,
        "AVPesado": null,
        "AVReconhecimento": null,
        "AVOutro": null,
        "NumeroMeiosAereosEnvolvidos": 0,
        "Latitude": 41.155310999999998,
        "Longitude": -8.5115309999999997,
        "DDD": null,
        "DMM": null,
        "DMS": null,
        "DataDosDados": 1768931120000,
        "Simbol": "24 - Em Despacho",
        "Status": 0,
        "Obs": null,
        "NumeroMeiosAquaticos": 0
      }
    },
    {
      "type": "Feature",
      "id": 5664118,
      "geometry": {
        "type": "Point",
        "coordinates": [
          -8.0981129997646253,
          39.804564999910625
        ]
      },
      "properties": {
        "OBJECTID": 5664118,
        "ID_oc": 26614910,
        "Numero": 20260092923,
        "Ano": null,
        "DataInicioOcorrencia": "2026-01-20T17:15:00",
        "DataOcorrencia": 1768932900000,
        "Data": 1768929300000,
        "Hora": null,
        "Duracao": null,
        "DuracaoMinutos": null,
        "FaseIncendio": null,
        "GrupoOc": null,
        "GrupoOc_ID": null,
        "CodNatureza": 2101,
        "IDFamilia": null,
        "Familia": null,
        "IDEspecie": null,
        "Especie": null,
        "IDTipo": null,
        "Tipo": null,
        "Natureza": "Habitacional",
        "CodImportancia": null,
        "Importancia": null,
        "CodEstadoOcorrencia": null,
        "EstadoOcorrencia": "Conclusão",
        "EstadoAgrupado": "Em Conclusão",
        "CREPC_ID": null,
        "CSREPC": "Beira Baixa",
        "CSREPC_ID": null,
        "CREPC": "Centro",
        "DI": null,
        "Distrito": null,
        "NUT_III": null,
        "CIM": null,
        "DICO": null,
        "Concelho": "Sertã",
        "DICOFRE": null,
        "Freguesia": "Sertã",
        "Localidade": "SERTÃ",
        "Endereco": null,
        "EntidadeResponsavel": null,
        "EntidadeGestora": null,
        "PCO": null,
        "COS": null,
        "UltimoPOSIT": null,
        "QuantEntidades": null,
        "RHBombeiros": null,
        "RHFEPC": null,
        "RHUEPS": null,
        "RHGNR": null,
        "RHPSP": null,
        "RHESF": null,
        "RHFA": null,
        "RHINEM": null,
        "RHOutros": null,
        "NumeroOperacionaisTerrestresEnv": null,
        "Operacionais": 9,
        "NumeroOperacionaisAereosEnvolvi": null,
        "RTBombeiros": null,
        "RTFEPC": null,
        "RTUEPS": null,
        "RTGNR": null,
        "RTPSP": null,
        "RTESF": null,
        "RTFA": null,
        "RTINEM": null,
        "RTOutros": null,
        "NumeroMeiosTerrestresEnvolvidos": 3,
        "GruposReforco": null,
        "HELigeiro": null,
        "HEPesado": null,
        "HECoordenacao": null,
        "HEOutro": null,
        "AVMedio": null,
        "AVPesado": null,
        "AVReconhecimento": null,
        "AVOutro": null,
        "NumeroMeiosAereosEnvolvidos": 0,
        "Latitude": 39.804564999999997,
        "Longitude": -8.0981129999999997,
        "DDD": null,
        "DMM": null,
        "DMS": null,
        "DataDosDados": 1768931120000,
        "Simbol": "21 - Em Conclusão",
        "Status": 0,
        "Obs": null,
        "NumeroMeiosAquaticos": 0
      }
    },
    {
      "type": "Feature",
      "id": 5664119,
      "geometry": {
        "type": "Point",
        "coordinates": [
          -8.1473519996797226,
          40.824593000447521
        ]
      },
      "properties": {
        "OBJECTID": 5664119,
        "ID_oc": 26612671,
        "Numero": 20260090684,
        "Ano": null,
        "DataInicioOcorrencia": "2026-01-20T09:55:00",
        "DataOcorrencia": 1768906500000,
        "Data": 1768902900000,
        "Hora": null,
        "Duracao": null,
        "DuracaoMinutos": null,
        "FaseIncendio": null,
        "GrupoOc": null,
        "GrupoOc_ID": null,
        "CodNatureza": 3109,
        "IDFamilia": null,
        "Familia": null,
        "IDEspecie": null,
        "Especie": null,
        "IDTipo": null,
        "Tipo": null,
        "Natureza": "Gestão de Combustível",
        "CodImportancia": null,
        "Importancia": null,
        "CodEstadoOcorrencia": null,
        "EstadoOcorrencia": "Em Curso",
        "EstadoAgrupado": "Em Curso",
        "CREPC_ID": null,
        "CSREPC": "Viseu Dão Lafões",
        "CSREPC_ID": null,
        "CREPC": "Centro",
        "DI": null,
        "Distrito": null,
        "NUT_III": null,
        "CIM": null,
        "DICO": null,
        "Concelho": "São Pedro do Sul",
        "DICOFRE": null,
        "Freguesia": "Carvalhais e Candal",
        "Localidade": "Coelheira",
        "Endereco": null,
        "EntidadeResponsavel": null,
        "EntidadeGestora": null,
        "PCO": null,
        "COS": null,
        "UltimoPOSIT": null,
        "QuantEntidades": null,
        "RHBombeiros": null,
        "RHFEPC": null,
        "RHUEPS": null,
        "RHGNR": null,
        "RHPSP": null,
        "RHESF": null,
        "RHFA": null,
        "RHINEM": null,
        "RHOutros": null,
        "NumeroOperacionaisTerrestresEnv": null,
        "Operacionais": 8,
        "NumeroOperacionaisAereosEnvolvi": null,
        "RTBombeiros": null,
        "RTFEPC": null,
        "RTUEPS": null,
        "RTGNR": null,
        "RTPSP": null,
        "RTESF": null,
        "RTFA": null,
        "RTINEM": null,
        "RTOutros": null,
        "NumeroMeiosTerrestresEnvolvidos": 2,
        "GruposReforco": null,
        "HELigeiro": null,
        "HEPesado": null,
        "HECoordenacao": null,
        "HEOutro": null,
        "AVMedio": null,
        "AVPesado": null,
        "AVReconhecimento": null,
        "AVOutro": null,
        "NumeroMeiosAereosEnvolvidos": 0,
        "Latitude": 40.824593,
        "Longitude": -8.1473519999999997,
        "DDD": null,
        "DMM": null,
        "DMS": null,
        "DataDosDados": 1768931120000,
        "Simbol": "31 - Em Curso",
        "Status": 0,
        "Obs": null,
        "NumeroMeiosAquaticos": 0
      }
    },
    {
      "type": "Feature",
      "id": 5664120,
      "geometry": {
        "type": "Point",
        "coordinates": [
          -8.6534930005718351,
          40.517244000313369
        ]
      },
      "properties": {
        "OBJECTID": 5664120,
        "ID_oc": 26614944,
        "Numero": 20260092957,
        "Ano": null,
        "DataInicioOcorrencia": "2026-01-20T17:20:00",
        "DataOcorrencia": 1768933200000,
        "Data": 1768929600000,
        "Hora": null,
        "Duracao": null,
        "DuracaoMinutos": null,
        "FaseIncendio": null,
        "GrupoOc": null,
        "GrupoOc_ID": null,
        "CodNatureza": 4331,
        "IDFamilia": null,
        "Familia": null,
        "IDEspecie": null,
        "Especie": null,
        "IDTipo": null,
        "Tipo": null,
        "Natureza": "Busca e Resgate Terrestre, de Animais",
        "CodImportancia": null,
        "Importancia": null,
        "CodEstadoOcorrencia": null,
        "EstadoOcorrencia": "Em Resolução",
        "EstadoAgrupado": "Em Resolução",
        "CREPC_ID": null,
        "CSREPC": "Região de Aveiro",
        "CSREPC_ID": null,
        "CREPC": "Centro",
        "DI": null,
        "Distrito": null,
        "NUT_III": null,
        "CIM": null,
        "DICO": null,
        "Concelho": "Vagos",
        "DICOFRE": null,
        "Freguesia": "Ouca",
        "Localidade": "OUCA",
        "Endereco": null,
        "EntidadeResponsavel": null,
        "EntidadeGestora": null,
        "PCO": null,
        "COS": null,
        "UltimoPOSIT": null,
        "QuantEntidades": null,
        "RHBombeiros": null,
        "RHFEPC": null,
        "RHUEPS": null,
        "RHGNR": null,
        "RHPSP": null,
        "RHESF": null,
        "RHFA": null,
        "RHINEM": null,
        "RHOutros": null,
        "NumeroOperacionaisTerrestresEnv": null,
        "Operacionais": 2,
        "NumeroOperacionaisAereosEnvolvi": null,
        "RTBombeiros": null,
        "RTFEPC": null,
        "RTUEPS": null,
        "RTGNR": null,
        "RTPSP": null,
        "RTESF": null,
        "RTFA": null,
        "RTINEM": null,
        "RTOutros": null,
        "NumeroMeiosTerrestresEnvolvidos": 1,
        "GruposReforco": null,
        "HELigeiro": null,
        "HEPesado": null,
        "HECoordenacao": null,
        "HEOutro": null,
        "AVMedio": null,
        "AVPesado": null,
        "AVReconhecimento": null,
        "AVOutro": null,
        "NumeroMeiosAereosEnvolvidos": 0,
        "Latitude": 40.517243999999998,
        "Longitude": -8.6534929999999992,
        "DDD": null,
        "DMM": null,
        "DMS": null,
        "DataDosDados": 1768931120000,
        "Simbol": "43 - Em Resolução",
        "Status": 0,
        "Obs": null,
        "NumeroMeiosAquaticos": 0
      }
    },
    {
      "type": "Feature",
      "id": 5664121,
      "geometry": {
        "type": "Point",
        "coordinates": [
          -8.5562420003835555,
          41.18309400013981
        ]
      },
      "properties": {
        "OBJECTID": 5664121,
        "ID_oc": 26615046,
        "Numero": 20260093059,
        "Ano": null,
        "DataInicioOcorrencia": "2026-01-20T17:40:00",
        "DataOcorrencia": 1768934400000,
        "Data": 1768930800000,
        "Hora": null,
        "Duracao": null,
        "DuracaoMinutos": null,
        "FaseIncendio": null,
        "GrupoOc": null,
        "GrupoOc_ID": null,
        "CodNatureza": 2401,
        "IDFamilia": null,
        "Familia": null,
        "IDEspecie": null,
        "Especie": null,
        "IDTipo": null,
        "Tipo": null,
        "Natureza": "Atropelamento rodoviário",
        "CodImportancia": null,
        "Importancia": null,
        "CodEstadoOcorrencia": null,
        "EstadoOcorrencia": "Despacho de 1.º Alerta",
        "EstadoAgrupado": "Em Despacho",
        "CREPC_ID": null,
        "CSREPC": "Area M. Porto",
        "CSREPC_ID": null,
        "CREPC": "Norte",
        "DI": null,
        "Distrito": null,
        "NUT_III": null,
        "CIM": null,
        "DICO": null,
        "Concelho": "Gondomar",
        "DICOFRE": null,
        "Freguesia": "Rio Tinto",
        "Localidade": "Rio Tinto",
        "Endereco": null,
        "EntidadeResponsavel": null,
        "EntidadeGestora": null,
        "PCO": null,
        "COS": null,
        "UltimoPOSIT": null,
        "QuantEntidades": null,
        "RHBombeiros": null,
        "RHFEPC": null,
        "RHUEPS": null,
        "RHGNR": null,
        "RHPSP": null,
        "RHESF": null,
        "RHFA": null,
        "RHINEM": null,
        "RHOutros": null,
        "NumeroOperacionaisTerrestresEnv": null,
        "Operacionais": 2,
        "NumeroOperacionaisAereosEnvolvi": null,
        "RTBombeiros": null,
        "RTFEPC": null,
        "RTUEPS": null,
        "RTGNR": null,
        "RTPSP": null,
        "RTESF": null,
        "RTFA": null,
        "RTINEM": null,
        "RTOutros": null,
        "NumeroMeiosTerrestresEnvolvidos": 1,
        "GruposReforco": null,
        "HELigeiro": null,
        "HEPesado": null,
        "HECoordenacao": null,
        "HEOutro": null,
        "AVMedio": null,
        "AVPesado": null,
        "AVReconhecimento": null,
        "AVOutro": null,
        "NumeroMeiosAereosEnvolvidos": 0,
        "Latitude": 41.183093999999997,
        "Longitude": -8.5562419999999992,
        "DDD": null,
        "DMM": null,
        "DMS": null,
        "DataDosDados": 1768931120000,
        "Simbol": "24 - Em Despacho",
        "Status": 0,
        "Obs": null,
        "NumeroMeiosAquaticos": 0
      }
    },
    {
      "type": "Feature",
      "id": 5664122,
      "geometry": {
        "type": "Point",
        "coordinates": [
          -8.5087019994294124,
          40.819267000425747
        ]
      },
      "properties": {
        "OBJECTID": 5664122,
        "ID_oc": 26614942,
        "Numero": 20260092955,
        "Ano": null,
        "DataInicioOcorrencia": "2026-01-20T17:12:00",
        "DataOcorrencia": 1768932720000,
        "Data": 1768929120000,
        "Hora": null,
        "Duracao": null,
        "DuracaoMinutos": null,
        "FaseIncendio": null,
        "GrupoOc": null,
        "GrupoOc_ID": null,
        "CodNatureza": 2403,
        "IDFamilia": null,
        "Familia": null,
        "IDEspecie": null,
        "Especie": null,
        "IDTipo": null,
        "Tipo": null,
        "Natureza": "Colisão rodoviária",
        "CodImportancia": null,
        "Importancia": null,
        "CodEstadoOcorrencia": null,
        "EstadoOcorrencia": "Chegada ao TO",
        "EstadoAgrupado": "Em Despacho",
        "CREPC_ID": null,
        "CSREPC": "Area M. Porto",
        "CSREPC_ID": null,
        "CREPC": "Norte",
        "DI": null,
        "Distrito": null,
        "NUT_III": null,
        "CIM": null,
        "DICO": null,
        "Concelho": "Oliveira de Azeméis",
        "DICOFRE": null,
        "Freguesia": "O. Azeméis, Riba-Ul, Ul, Macinhata Seixa, Madail",
        "Localidade": "Ul",
        "Endereco": null,
        "EntidadeResponsavel": null,
        "EntidadeGestora": null,
        "PCO": null,
        "COS": null,
        "UltimoPOSIT": null,
        "QuantEntidades": null,
        "RHBombeiros": null,
        "RHFEPC": null,
        "RHUEPS": null,
        "RHGNR": null,
        "RHPSP": null,
        "RHESF": null,
        "RHFA": null,
        "RHINEM": null,
        "RHOutros": null,
        "NumeroOperacionaisTerrestresEnv": null,
        "Operacionais": 4,
        "NumeroOperacionaisAereosEnvolvi": null,
        "RTBombeiros": null,
        "RTFEPC": null,
        "RTUEPS": null,
        "RTGNR": null,
        "RTPSP": null,
        "RTESF": null,
        "RTFA": null,
        "RTINEM": null,
        "RTOutros": null,
        "NumeroMeiosTerrestresEnvolvidos": 2,
        "GruposReforco": null,
        "HELigeiro": null,
        "HEPesado": null,
        "HECoordenacao": null,
        "HEOutro": null,
        "AVMedio": null,
        "AVPesado": null,
        "AVReconhecimento": null,
        "AVOutro": null,
        "NumeroMeiosAereosEnvolvidos": 0,
        "Latitude": 40.819267000000004,
        "Longitude": -8.5087019999999995,
        "DDD": null,
        "DMM": null,
        "DMS": null,
        "DataDosDados": 1768931120000,
        "Simbol": "24 - Em Despacho",
        "Status": 0,
        "Obs": null,
        "NumeroMeiosAquaticos": 0
      }
    },
    {
      "type": "Feature",
      "id": 5664123,
      "geometry": {
        "type": "Point",
        "coordinates": [
          -9.2434209999432113,
          38.725234000349282
        ]
      },
      "properties": {
        "OBJECTID": 5664123,
        "ID_oc": 26589489,
        "Numero": 20260067504,
        "Ano": null,
        "DataInicioOcorrencia": "2026-01-15T03:00:00",
        "DataOcorrencia": 1768449600000,
        "Data": 1768446000000,
        "Hora": null,
        "Duracao": null,
        "DuracaoMinutos": null,
        "FaseIncendio": null,
        "GrupoOc": null,
        "GrupoOc_ID": null,
        "CodNatureza": 9119,
        "IDFamilia": null,
        "Familia": null,
        "IDEspecie": null,
        "Especie": null,
        "IDTipo": null,
        "Tipo": null,
        "Natureza": "Missões Internacionais de Assistência",
        "CodImportancia": null,
        "Importancia": null,
        "CodEstadoOcorrencia": null,
        "EstadoOcorrencia": "Em Curso",
        "EstadoAgrupado": "Em Curso",
        "CREPC_ID": null,
        "CSREPC": "Grande Lisboa",
        "CSREPC_ID": null,
        "CREPC": "Lisboa e Vale do Tejo",
        "DI": null,
        "Distrito": null,
        "NUT_III": null,
        "CIM": null,
        "DICO": null,
        "Concelho": "Oeiras",
        "DICOFRE": null,
        "Freguesia": "Carnaxide e Queijas",
        "Localidade": "CNEPC",
        "Endereco": null,
        "EntidadeResponsavel": null,
        "EntidadeGestora": null,
        "PCO": null,
        "COS": null,
        "UltimoPOSIT": null,
        "QuantEntidades": null,
        "RHBombeiros": null,
        "RHFEPC": null,
        "RHUEPS": null,
        "RHGNR": null,
        "RHPSP": null,
        "RHESF": null,
        "RHFA": null,
        "RHINEM": null,
        "RHOutros": null,
        "NumeroOperacionaisTerrestresEnv": null,
        "Operacionais": 3,
        "NumeroOperacionaisAereosEnvolvi": null,
        "RTBombeiros": null,
        "RTFEPC": null,
        "RTUEPS": null,
        "RTGNR": null,
        "RTPSP": null,
        "RTESF": null,
        "RTFA": null,
        "RTINEM": null,
        "RTOutros": null,
        "NumeroMeiosTerrestresEnvolvidos": 0,
        "GruposReforco": null,
        "HELigeiro": null,
        "HEPesado": null,
        "HECoordenacao": null,
        "HEOutro": null,
        "AVMedio": null,
        "AVPesado": null,
        "AVReconhecimento": null,
        "AVOutro": null,
        "NumeroMeiosAereosEnvolvidos": 0,
        "Latitude": 38.725234,
        "Longitude": -9.2434209999999997,
        "DDD": null,
        "DMM": null,
        "DMS": null,
        "DataDosDados": 1768931120000,
        "Simbol": "91 - Em Curso",
        "Status": 0,
        "Obs": null,
        "NumeroMeiosAquaticos": 0
      }
    },
    {
      "type": "Feature",
      "id": 5664124,
      "geometry": {
        "type": "Point",
        "coordinates": [
          -8.9757150001418449,
          38.702322999889759
        ]
      },
      "properties": {
        "OBJECTID": 5664124,
        "ID_oc": 26614661,
        "Numero": 20260092674,
        "Ano": null,
        "DataInicioOcorrencia": "2026-01-20T16:14:00",
        "DataOcorrencia": 1768929240000,
        "Data": 1768925640000,
        "Hora": null,
        "Duracao": null,
        "DuracaoMinutos": null,
        "FaseIncendio": null,
        "GrupoOc": null,
        "GrupoOc_ID": null,
        "CodNatureza": 2401,
        "IDFamilia": null,
        "Familia": null,
        "IDEspecie": null,
        "Especie": null,
        "IDTipo": null,
        "Tipo": null,
        "Natureza": "Atropelamento rodoviário",
        "CodImportancia": null,
        "Importancia": null,
        "CodEstadoOcorrencia": null,
        "EstadoOcorrencia": "Conclusão",
        "EstadoAgrupado": "Em Conclusão",
        "CREPC_ID": null,
        "CSREPC": "Península de Setúbal",
        "CSREPC_ID": null,
        "CREPC": "Lisboa e Vale do Tejo",
        "DI": null,
        "Distrito": null,
        "NUT_III": null,
        "CIM": null,
        "DICO": null,
        "Concelho": "Montijo",
        "DICOFRE": null,
        "Freguesia": "Montijo e Afonsoeiro",
        "Localidade": "Montijo",
        "Endereco": null,
        "EntidadeResponsavel": null,
        "EntidadeGestora": null,
        "PCO": null,
        "COS": null,
        "UltimoPOSIT": null,
        "QuantEntidades": null,
        "RHBombeiros": null,
        "RHFEPC": null,
        "RHUEPS": null,
        "RHGNR": null,
        "RHPSP": null,
        "RHESF": null,
        "RHFA": null,
        "RHINEM": null,
        "RHOutros": null,
        "NumeroOperacionaisTerrestresEnv": null,
        "Operacionais": 9,
        "NumeroOperacionaisAereosEnvolvi": null,
        "RTBombeiros": null,
        "RTFEPC": null,
        "RTUEPS": null,
        "RTGNR": null,
        "RTPSP": null,
        "RTESF": null,
        "RTFA": null,
        "RTINEM": null,
        "RTOutros": null,
        "NumeroMeiosTerrestresEnvolvidos": 3,
        "GruposReforco": null,
        "HELigeiro": null,
        "HEPesado": null,
        "HECoordenacao": null,
        "HEOutro": null,
        "AVMedio": null,
        "AVPesado": null,
        "AVReconhecimento": null,
        "AVOutro": null,
        "NumeroMeiosAereosEnvolvidos": 0,
        "Latitude": 38.702323,
        "Longitude": -8.9757149999999992,
        "DDD": null,
        "DMM": null,
        "DMS": null,
        "DataDosDados": 1768931120000,
        "Simbol": "24 - Em Conclusão",
        "Status": 0,
        "Obs": null,
        "NumeroMeiosAquaticos": 0
      }
    }
  ]
}
